dict2obj/__init__.py
dict2obj/dict2obj.py
dict2object-1.0.0.dist-info/LICENSE.txt
dict2object-1.0.0.dist-info/METADATA
dict2object-1.0.0.dist-info/WHEEL
dict2object-1.0.0.dist-info/entry_points.txt
dict2object-1.0.0.dist-info/top_level.txt
dict2object-1.0.0.dist-info/RECORD
